zcpm/__init__.py
zcpm/unit.py
zcpm-0.1.dist-info/METADATA
zcpm-0.1.dist-info/WHEEL
zcpm-0.1.dist-info/top_level.txt
zcpm-0.1.dist-info/RECORD
