Metadata-Version: 2.1
Name: zcpm
Version: 0.1
Requires-Dist: numpy
